Topsis_Pawandeep_101917092.py
Topsis_Pawandeep_101917092-0.0.1.dist-info/LICENSE
Topsis_Pawandeep_101917092-0.0.1.dist-info/METADATA
Topsis_Pawandeep_101917092-0.0.1.dist-info/WHEEL
Topsis_Pawandeep_101917092-0.0.1.dist-info/top_level.txt
Topsis_Pawandeep_101917092-0.0.1.dist-info/RECORD
