Metadata-Version: 2.1
Name: Topsis-Pawandeep-101917092
Version: 0.0.1
Summary: Topsis package for Predictive Analysis Assignement made by Pawandeep_101917092
Home-page: UNKNOWN
Author: Pawandeep Singh
License: UNKNOWN
Keywords: pawandeep
Platform: UNKNOWN
Classifier: Programming Language :: Python :: 3
Classifier: License :: OSI Approved :: MIT License
Classifier: Operating System :: OS Independent
Requires-Python: >=3.6
Requires-Dist: pandas
